dnd5apy/__init__.py
dnd5apy/api/__init__.py
dnd5apy/api/character_data_api.py
dnd5apy/api/class_api.py
dnd5apy/api/class_levels_api.py
dnd5apy/api/class_resource_lists_api.py
dnd5apy/api/common_api.py
dnd5apy/api/equipment_api.py
dnd5apy/api/feats_api.py
dnd5apy/api/features_api.py
dnd5apy/api/game_mechanics_api.py
dnd5apy/api/monsters_api.py
dnd5apy/api/races_api.py
dnd5apy/api/rules_api.py
dnd5apy/api/spells_api.py
dnd5apy/api/subclasses_api.py
dnd5apy/api/subraces_api.py
dnd5apy/api/traits_api.py
dnd5apy/api_client.py
dnd5apy/api_response.py
dnd5apy/configuration.py
dnd5apy/exceptions.py
dnd5apy/models/__init__.py
dnd5apy/models/ability_bonus.py
dnd5apy/models/ability_score.py
dnd5apy/models/alignment.py
dnd5apy/models/api_reference.py
dnd5apy/models/api_reference_list.py
dnd5apy/models/area_of_effect.py
dnd5apy/models/armor.py
dnd5apy/models/background.py
dnd5apy/models/background_all_of_feature.py
dnd5apy/models/choice.py
dnd5apy/models/class_all_of_starting_equipment.py
dnd5apy/models/class_level.py
dnd5apy/models/class_level_class_specific.py
dnd5apy/models/class_level_class_specific_any_of.py
dnd5apy/models/class_level_class_specific_any_of1.py
dnd5apy/models/class_level_class_specific_any_of10.py
dnd5apy/models/class_level_class_specific_any_of11.py
dnd5apy/models/class_level_class_specific_any_of2.py
dnd5apy/models/class_level_class_specific_any_of3.py
dnd5apy/models/class_level_class_specific_any_of4.py
dnd5apy/models/class_level_class_specific_any_of5.py
dnd5apy/models/class_level_class_specific_any_of5_martial_arts.py
dnd5apy/models/class_level_class_specific_any_of6.py
dnd5apy/models/class_level_class_specific_any_of7.py
dnd5apy/models/class_level_class_specific_any_of8.py
dnd5apy/models/class_level_class_specific_any_of9.py
dnd5apy/models/class_level_class_specific_any_of9_creating_spell_slots_inner.py
dnd5apy/models/condition.py
dnd5apy/models/cost.py
dnd5apy/models/damage.py
dnd5apy/models/damage_at_character_level.py
dnd5apy-1.0.0.dist-info/METADATA
dnd5apy-1.0.0.dist-info/WHEEL
dnd5apy-1.0.0.dist-info/RECORD
